softioc/__init__.py
softioc/__main__.py
softioc/_extension.cpython-311-darwin.so
softioc/_version_git.py
softioc/access.acf
softioc/alarm.py
softioc/asyncio_dispatcher.py
softioc/autosave.py
softioc/builder.py
softioc/cothread_dispatcher.py
softioc/device.dbd
softioc/device.py
softioc/device_core.py
softioc/fields.py
softioc/imports.py
softioc/pvlog.py
softioc/pythonSoftIoc.py
softioc/softioc.py
softioc/iocStats/devIocStats/Makefile
softioc/iocStats/devIocStats/devIocStats.dbd
softioc/iocStats/devIocStats/devIocStats.h
softioc/iocStats/devIocStats/devIocStatsAnalog.c
softioc/iocStats/devIocStats/devIocStatsString.c
softioc/iocStats/devIocStats/devIocStatsSub.c
softioc/iocStats/devIocStats/devIocStatsTest.c
softioc/iocStats/devIocStats/devIocStatsWaveform.c
softioc/iocStats/devIocStats/devVxStats.dbd
softioc/iocStats/devIocStats/os/Darwin/devIocStatsOSD.h
softioc/iocStats/devIocStats/os/Linux/osdCpuUsage.c
softioc/iocStats/devIocStats/os/Linux/osdCpuUtilization.c
softioc/iocStats/devIocStats/os/Linux/osdFdUsage.c
softioc/iocStats/devIocStats/os/Linux/osdMemUsage.c
softioc/iocStats/devIocStats/os/WIN32/devIocStatsOSD.h
softioc/iocStats/devIocStats/os/WIN32/osdBootInfo.c
softioc/iocStats/devIocStats/os/WIN32/osdCpuUtilization.c
softioc/iocStats/devIocStats/os/WIN32/osdFdUsage.c
softioc/iocStats/devIocStats/os/WIN32/osdHostInfo.c
softioc/iocStats/devIocStats/os/WIN32/osdMemUsage.c
softioc/iocStats/devIocStats/os/WIN32/osdSystemInfo.c
softioc/iocStats/devIocStats/os/default/devIocStatsOSD.h
softioc/iocStats/devIocStats/os/default/osdBootInfo.c
softioc/iocStats/devIocStats/os/default/osdClustInfo.c
softioc/iocStats/devIocStats/os/default/osdCpuUsage.c
softioc/iocStats/devIocStats/os/default/osdCpuUtilization.c
softioc/iocStats/devIocStats/os/default/osdFdUsage.c
softioc/iocStats/devIocStats/os/default/osdHostInfo.c
softioc/iocStats/devIocStats/os/default/osdIFErrors.c
softioc/iocStats/devIocStats/os/default/osdMemUsage.c
softioc-4.7.0.dist-info/licenses/LICENSE
softioc-4.7.0.dist-info/METADATA
softioc-4.7.0.dist-info/WHEEL
softioc-4.7.0.dist-info/entry_points.txt
softioc-4.7.0.dist-info/top_level.txt
softioc-4.7.0.dist-info/RECORD
