Metadata-Version: 2.4
Name: softioc
Version: 4.7.0
Summary: Embed an EPICS IOC in a Python process
Home-page: https://github.com/DiamondLightSource/pythonSoftIOC
Author: Michael Abbott
Author-email: Michael.Abbott@diamond.ac.uk
License: Apache License 2.0
Classifier: Development Status :: 5 - Production/Stable
Classifier: License :: OSI Approved :: Apache Software License
Classifier: Programming Language :: Python :: 3.7
Classifier: Programming Language :: Python :: 3.8
Classifier: Programming Language :: Python :: 3.9
Classifier: Programming Language :: Python :: 3.10
Requires-Python: >=3.7
License-File: LICENSE
Requires-Dist: epicscorelibs<7.0.10.99.1,>=7.0.10.99.0.0
Requires-Dist: pvxslibs>=1.3.2a2
Requires-Dist: numpy
Requires-Dist: epicsdbbuilder>=1.4
Requires-Dist: pyyaml>=6.0
Provides-Extra: useful
Requires-Dist: cothread; extra == "useful"
Requires-Dist: scipy; extra == "useful"
Requires-Dist: aioca>=1.6; extra == "useful"
Provides-Extra: dev
Requires-Dist: pytest-cov; extra == "dev"
Requires-Dist: pytest-flake8; extra == "dev"
Requires-Dist: flake8<5.0.0; extra == "dev"
Requires-Dist: sphinx==4.3.2; extra == "dev"
Requires-Dist: sphinx-rtd-theme==1.0.0; extra == "dev"
Requires-Dist: sphinx-rtd-theme-github-versions==1.1; extra == "dev"
Requires-Dist: pytest-asyncio; extra == "dev"
Requires-Dist: aioca>=1.6; extra == "dev"
Requires-Dist: cothread; sys_platform != "win32" and extra == "dev"
Requires-Dist: p4p>=4.2.0a2; extra == "dev"
Dynamic: license-file
Dynamic: requires-dist
